data_flow_generator/__init__.py
data_flow_generator/dataflow.py
data_flow_generator/dataflow_command.py
data_flow_generator/dataflow_structs.py
data_flow_generator/exceptions.py
data_flow_generator/generate_data_flow.py
data_flow_generator/helpers.py
data_flow_generator/parser_register.py
data_flow_generator/parser_utils.py
data_flow_generator/path_utils.py
data_flow_generator/pyvis_mod.py
data_flow_generator/pyvis_styles.css
data_flow_generator/js/pyvis_components/core.js
data_flow_generator/js/pyvis_components/export.js
data_flow_generator/js/pyvis_components/hover_tooltips.js
data_flow_generator/js/pyvis_components/init.js
data_flow_generator/js/pyvis_components/keyboard.js
data_flow_generator/js/pyvis_components/loading.js
data_flow_generator/js/pyvis_components/node_actions.js
data_flow_generator/js/pyvis_components/panels.js
data_flow_generator/js/pyvis_components/search.js
data_flow_generator/js/pyvis_components/selection.js
data_flow_generator/js/pyvis_components/settings.js
data_flow_generator/js/pyvis_components/tooltips.js
data_flow_generator/parsers/__init__.py
data_flow_generator/parsers/parser_ansi.py
data_flow_generator/parsers/parser_denodo.py
data_flow_generator/parsers/parser_mysql.py
data_flow_generator/parsers/parser_oracle.py
data_flow_generator/parsers/parser_postgres.py
data_flow_generator/parsers/parser_snowflake.py
data_flow_generator/parsers/parser_sqlite.py
data_flow_generator/parsers/parser_sqlserver.py
data_flow_generator/parsers/parser_utils.py
data_flow_generator-0.2.4.dist-info/licenses/LICENSE
data_flow_generator-0.2.4.dist-info/METADATA
data_flow_generator-0.2.4.dist-info/WHEEL
data_flow_generator-0.2.4.dist-info/entry_points.txt
data_flow_generator-0.2.4.dist-info/top_level.txt
data_flow_generator-0.2.4.dist-info/RECORD
