Metadata-Version: 2.4
Name: data-flow-generator
Version: 0.2.4
Summary: Interactive data flow visualization tool for database dumps
Author-email: Jon-Mikkel Korsvik <jkorsvik@outlook.com>
License-Expression: MIT
Project-URL: Homepage, https://github.com/jkorsvik/dataflow-generator
Project-URL: Documentation, https://github.com/jkorsvik/dataflow-generator/blob/main/README.md
Keywords: dataflow,visualization,vql,denodo,diagram,data-flow-generator,generator
Classifier: Development Status :: 4 - Beta
Classifier: Intended Audience :: Developers
Classifier: Programming Language :: Python :: 3
Classifier: Programming Language :: Python :: 3.12
Requires-Python: >=3.12
License-File: LICENSE
Requires-Dist: colorama==0.4.6
Requires-Dist: narwhals==1.38.1
Requires-Dist: networkx==3.4.2
Requires-Dist: numpy>=2.2.4
Requires-Dist: packaging>=24.2
Requires-Dist: python-dotenv==1.1.0
Requires-Dist: pyvis>=0.3.2
Requires-Dist: rapidfuzz==3.13.0
Requires-Dist: readchar==4.2.1
Requires-Dist: questionary>=2.0.1
Requires-Dist: pandas-stubs>=2.2.3.250308
Requires-Dist: types-pygments>=2.19.0.20250305
Requires-Dist: types-colorama>=0.4.15.20240311
Requires-Dist: types-networkx>=3.4.2.20250507
Requires-Dist: platformdirs>=4.2.2
Requires-Dist: sqlfluff>=3.4.0
Requires-Dist: sqlparse>=0.5.3
Requires-Dist: sqlglot[rs]>=26.16.4
Provides-Extra: dev
Requires-Dist: mypy>=1.15.0; extra == "dev"
Requires-Dist: pytest>=8.3.5; extra == "dev"
Requires-Dist: pytest-cov>=4.0; extra == "dev"
Requires-Dist: anybadge>=1.16.0; extra == "dev"
Dynamic: license-file
